StreamlitGauth/__init__.py
StreamlitGauth/google_auth.py
StreamlitGAuth-2.0.9.dist-info/METADATA
StreamlitGAuth-2.0.9.dist-info/WHEEL
StreamlitGAuth-2.0.9.dist-info/top_level.txt
StreamlitGAuth-2.0.9.dist-info/RECORD
