Metadata-Version: 2.1
Name: StreamlitGAuth
Version: 2.0.9
Summary: st_googleauth is a Python library that provides Streamlit integration for Google Authenticator. It enables single sign-on (SSO) with Google Authenticator for Streamlit applications.
Author: rahul katoch
Author-email: rahulkatoch99@gmail.com
Maintainer: Rahul Katoch
Maintainer-email: rahulkatoch99@gmail.com
License: MIT
Keywords: streamlit google-authenticator SSO goole_oauth
Classifier: Development Status :: 5 - Production/Stable
Classifier: Intended Audience :: Developers
Classifier: License :: OSI Approved :: MIT License
Classifier: Programming Language :: Python :: 3
Classifier: Programming Language :: Python :: 3.6
Classifier: Programming Language :: Python :: 3.7
Classifier: Programming Language :: Python :: 3.8
Classifier: Programming Language :: Python :: 3.9
Classifier: Programming Language :: Python :: 3.10
Requires-Python: >=3.6
